beaconled/__init__.py
beaconled/cli.py
beaconled/exceptions.py
beaconled/analytics/__init__.py
beaconled/analytics/collaboration_analyzer.py
beaconled/analytics/coverage_analyzer.py
beaconled/analytics/engine.py
beaconled/analytics/models.py
beaconled/analytics/quality_analyzer.py
beaconled/analytics/risk_analyzer.py
beaconled/analytics/time_analyzer.py
beaconled/core/__init__.py
beaconled/core/analyzer.py
beaconled/core/date_errors.py
beaconled/core/date_utils.py
beaconled/core/models.py
beaconled/formatters/__init__.py
beaconled/formatters/ascii_chart.py
beaconled/formatters/base_formatter.py
beaconled/formatters/chart.py
beaconled/formatters/extended.py
beaconled/formatters/heatmap.py
beaconled/formatters/json_format.py
beaconled/formatters/rich_formatter.py
beaconled/formatters/standard.py
beaconled/integrations/__init__.py
beaconled/utils/__init__.py
beaconled/utils/date_utils.py
beaconled/utils/performance.py
beaconled-0.5.0.dist-info/licenses/LICENSE
beaconled-0.5.0.dist-info/METADATA
beaconled-0.5.0.dist-info/WHEEL
beaconled-0.5.0.dist-info/entry_points.txt
beaconled-0.5.0.dist-info/top_level.txt
beaconled-0.5.0.dist-info/RECORD
