Metadata-Version: 2.4
Name: beaconled
Version: 0.5.0
Summary: Your delivery compass for empowered product builders. A comprehensive toolkit for analyzing git repository statistics and development metrics.
Author: shrwnsan
Maintainer: shrwnsan
License: MIT
Project-URL: Homepage, https://github.com/shrwnsan/beacon-delivery-compass
Project-URL: Documentation, https://github.com/shrwnsan/beacon-delivery-compass#readme
Project-URL: Repository, https://github.com/shrwnsan/beacon-delivery-compass.git
Project-URL: Issues, https://github.com/shrwnsan/beacon-delivery-compass/issues
Keywords: git,analytics,metrics,development,productivity
Classifier: Development Status :: 3 - Alpha
Classifier: Intended Audience :: Developers
Classifier: License :: OSI Approved :: MIT License
Classifier: Operating System :: OS Independent
Classifier: Programming Language :: Python :: 3
Classifier: Programming Language :: Python :: 3.10
Classifier: Programming Language :: Python :: 3.11
Classifier: Programming Language :: Python :: 3.12
Classifier: Topic :: Software Development :: Libraries :: Python Modules
Classifier: Topic :: Software Development :: Version Control :: Git
Requires-Python: >=3.10
License-File: LICENSE
Requires-Dist: click>=8.1.0
Requires-Dist: gitpython>=3.1.41
Requires-Dist: rich>=13.0.0
Requires-Dist: pydantic>=2.7.0
Requires-Dist: colorama>=0.4.6
Requires-Dist: defusedxml>=0.7.0
Provides-Extra: viz
Requires-Dist: matplotlib>=3.5.0; extra == "viz"
Requires-Dist: numpy>=1.21.0; extra == "viz"
Provides-Extra: dev
Requires-Dist: pytest>=7.0.0; extra == "dev"
Requires-Dist: pytest-cov>=4.0.0; extra == "dev"
Requires-Dist: pytest-mock>=3.0.0; extra == "dev"
Requires-Dist: pytest-xdist>=3.0.0; extra == "dev"
Requires-Dist: pytest-testmon>=2.0.0; extra == "dev"
Requires-Dist: hypothesis>=6.0.0; extra == "dev"
Requires-Dist: freezegun>=1.0.0; extra == "dev"
Requires-Dist: pytz>=2023.3; extra == "dev"
Requires-Dist: black>=23.0.0; extra == "dev"
Requires-Dist: ruff>=0.1.0; extra == "dev"
Requires-Dist: isort>=5.13.2; extra == "dev"
Requires-Dist: mypy>=1.0.0; extra == "dev"
Requires-Dist: typeguard>=4.0.0; extra == "dev"
Requires-Dist: types-python-dateutil>=2.8.0; extra == "dev"
Requires-Dist: types-pytz>=2023.0.0; extra == "dev"
Requires-Dist: types-requests>=2.28.0; extra == "dev"
Requires-Dist: types-colorama>=0.4.0; extra == "dev"
Requires-Dist: types-defusedxml>=0.7.0.20240215; extra == "dev"
Requires-Dist: pandas-stubs>=1.5.0; extra == "dev"
Requires-Dist: bandit>=1.7.0; extra == "dev"
Requires-Dist: pip-audit>=2.6.1; extra == "dev"
Requires-Dist: sphinx>=7.0.0; extra == "dev"
Requires-Dist: sphinx-rtd-theme>=1.0.0; extra == "dev"
Requires-Dist: myst-parser>=1.0.0; extra == "dev"
Requires-Dist: pre-commit>=3.0.0; extra == "dev"
Requires-Dist: ipdb>=0.13.0; extra == "dev"
Requires-Dist: ipython>=8.0.0; extra == "dev"
Provides-Extra: charts
Requires-Dist: matplotlib>=3.5.0; extra == "charts"
Requires-Dist: pandas>=1.5.0; extra == "charts"
Requires-Dist: numpy>=1.21.0; extra == "charts"
Dynamic: license-file
